{
  "algorithm_version": 2,
  "end_time": "Mon, 25 Jul 2022 01:19:19 GMT",
  "grade": "D-",
  "hidden": false,
  "likelihood_indicator": "MEDIUM",
  "response_headers": {
    "Connection": "Keep-Alive",
    "Content-Encoding": "gzip",
    "Content-Type": "text/html;charset=UTF-8",
    "Date": "Mon, 25 Jul 2022 01:19:08 GMT",
    "Keep-Alive": "timeout=15, max=500",
    "Referrer-Policy": "origin-when-cross-origin,strict-origin-when-cross-origin",
    "Server": "Microsoft-IIS/5.0",
    "Server-Timing": "dtSInfo;desc=\"0\", dtRpid;desc=\"1851028061\"",
    "Set-Cookie": "NEW_VISITOR=new; Expires=Tue, 26-Jul-2022 01:19:08 GMT; HttpOnly; Secure; SameSite=None, VISITOR=returning; Path=/pag_Home/index.html; HttpOnly; Secure; SameSite=None, JSESSIONID=34D894E10D33D5AF281F611651843B13; Path=/; Secure; HttpOnly; SameSite=None, dtCookie=v_4_srv_4_sn_9C3076D32CC401B688215FDF3102E590_perc_100000_ol_0_mul_1_app-3A7bd681314de07953_0; Path=/; Domain=.administracion.gob.es; HttpOnly; Secure; SameSite=None, TS01a8e1d0=01d9c3d318fef05aa4d8af2f1d13ba72fe03f0fd47ad76f92835b91991d05b099bf4bdf72fb68f67a379457b5a940c236c1419f9580bab68f6e75bee7115c4e2899fd66ece082c7abb94a952d2ad728baf8514e2e6; Path=/; HttpOnly; Secure; SameSite=None, TS013cc2a2=01d9c3d318c1cadef6bafd8862d0d4a0cbbec90011ad76f92835b91991d05b099bf4bdf72fb878b6862c9bb8cafaec549c53e40d8cba4c6290c6f8ba4199bfa5240a93bede; path=/pag_Home/index.html; HttpOnly; Secure; SameSite=None, TS011faf93=01d9c3d318199932aef795835e9fde851c05fb654ead76f92835b91991d05b099bf4bdf72fef52274482de46db80b3f6d855ac42bbd0a5d08e0334f91fc48bb7e964aa9357; path=/; domain=.administracion.gob.es; HttpOnly; Secure; SameSite=None",
    "Strict-Transport-Security": "max-age=63072000; preload",
    "Transfer-Encoding": "chunked",
    "Vary": "Accept-Encoding",
    "X-Content-Type-Options": "nosniff",
    "X-Frame-Options": "SAMEORIGIN",
    "X-OneAgent-JS-Injection": "true, true",
    "X-XSS-Protection": "1;mode=block"
  },
  "scan_id": 28021824,
  "score": 25,
  "start_time": "Mon, 25 Jul 2022 01:19:05 GMT",
  "state": "FINISHED",
  "status_code": 200,
  "tests_failed": 2,
  "tests_passed": 10,
  "tests_quantity": 12
}