{
  "algorithm_version": 2,
  "end_time": "Mon, 20 Feb 2023 01:08:41 GMT",
  "grade": "D-",
  "hidden": false,
  "likelihood_indicator": "MEDIUM",
  "response_headers": {
    "Connection": "Keep-Alive",
    "Content-Encoding": "gzip",
    "Content-Type": "text/html;charset=UTF-8",
    "Date": "Mon, 20 Feb 2023 01:08:27 GMT",
    "Keep-Alive": "timeout=15, max=500",
    "Referrer-Policy": "origin-when-cross-origin,strict-origin-when-cross-origin",
    "Server": "Microsoft-IIS/5.0",
    "Server-Timing": "dtSInfo;desc=\"0\", dtRpid;desc=\"-764988282\"",
    "Set-Cookie": "NEW_VISITOR=new; Expires=Tue, 21-Feb-2023 01:08:27 GMT; HttpOnly; Secure; SameSite=None, VISITOR=returning; Path=/pag_Home/index.html; HttpOnly; Secure; SameSite=None, JSESSIONID=FE0E46C9675D350F9664ED1275540249; Path=/; Secure; HttpOnly; SameSite=None, dtCookie=v_4_srv_3_sn_44A205D04C001439277673B6C8EB3955_perc_100000_ol_0_mul_1_app-3A7bd681314de07953_1; Path=/; Domain=.administracion.gob.es; HttpOnly; Secure; SameSite=None, TS01a8e1d0=01d9c3d31816836f934da4ddfc6915d78bbaa8a1afb76703bd02e7c08e656bfe5c6827218f14d297886aeeb50f97b9042aa71bf3f67439aca7ee9ffaaf9d62d1e6d9ce417a3c49d2cb8fa61a4b0d43010453798a96; Path=/; HttpOnly; Secure; SameSite=None, TS013cc2a2=01d9c3d3185316b19d117d4c9158f8b1eba33f86fdb76703bd02e7c08e656bfe5c6827218f30e1f22e0a3bb71377a783d6768fe086b7adaa6e91c4b4aa236d5e5532301fa1; path=/pag_Home/index.html; HttpOnly; Secure; SameSite=None, TS011faf93=01d9c3d318981e76ac1e527cc7c4addb4b248d3749b76703bd02e7c08e656bfe5c6827218f463bfbe2bad486351a2a2efc783bb8e921ad5bbe6559f3cdae9770b4ec4c70da; path=/; domain=.administracion.gob.es; HttpOnly; Secure; SameSite=None",
    "Strict-Transport-Security": "max-age=63072000; preload",
    "Transfer-Encoding": "chunked",
    "Vary": "Accept-Encoding",
    "X-Content-Type-Options": "nosniff",
    "X-Frame-Options": "SAMEORIGIN",
    "X-OneAgent-JS-Injection": "true, true",
    "X-XSS-Protection": "1;mode=block"
  },
  "scan_id": 34483915,
  "score": 25,
  "start_time": "Mon, 20 Feb 2023 01:08:22 GMT",
  "state": "FINISHED",
  "status_code": 200,
  "tests_failed": 2,
  "tests_passed": 10,
  "tests_quantity": 12
}