{
  "algorithm_version": 3,
  "end_time": "Mon, 08 Apr 2024 00:54:39 GMT",
  "grade": "F",
  "hidden": false,
  "likelihood_indicator": "MEDIUM",
  "response_headers": {
    "Connection": "Keep-Alive",
    "Content-Encoding": "gzip",
    "Content-Type": "text/html;charset=UTF-8",
    "Date": "Mon, 08 Apr 2024 00:54:37 GMT",
    "Keep-Alive": "timeout=15, max=500",
    "Referrer-Policy": "origin-when-cross-origin,strict-origin-when-cross-origin",
    "Server": "Microsoft-IIS/5.0",
    "Server-Timing": "dtSInfo;desc=\"0\", dtRpid;desc=\"-281937659\"",
    "Set-Cookie": "NEW_VISITOR=new; Expires=Tue, 09-Apr-2024 00:54:37 GMT; HttpOnly; Secure; SameSite=None, VISITOR=returning; Path=/pag_Home/index.html; HttpOnly; Secure; SameSite=None, JSESSIONID=16CB1813DC569B0FAC9CABCC6004C647; Path=/; Secure; HttpOnly; SameSite=None, TS01a8e1d0=01d9c3d3189d5ddba69c477617ffaf08992500d90cc249fddbfaef1a2cc58e47c15b2f9a09b549933e08464cd2f5eea32d0d5cff07d423267cdd429bf45ac70aba4332a2f0b3e41b968fedab04cc5c1abd85f665b1; Path=/; HttpOnly; Secure; SameSite=None, TS013cc2a2=01d9c3d318d1ce6213013369119b4ef1f18de0b56ec249fddbfaef1a2cc58e47c15b2f9a09a547b7b2b82e6a4ded9a164a62839240be54cf971c130a77f7cb580ec2482b60; path=/pag_Home/index.html; HttpOnly; Secure; SameSite=None, dtCookie=v_4_srv_4_sn_B49DC8E968563B678338C0B2E939D4C8_perc_100000_ol_0_mul_1_app-3A7bd681314de07953_0; Path=/; Domain=.administracion.gob.es",
    "Strict-Transport-Security": "max-age=63072000; preload",
    "Transfer-Encoding": "chunked",
    "Vary": "Accept-Encoding",
    "X-Content-Type-Options": "nosniff",
    "X-Frame-Options": "SAMEORIGIN",
    "X-OneAgent-JS-Injection": "true, true",
    "X-XSS-Protection": "1;mode=block"
  },
  "scan_id": 49789557,
  "score": 20,
  "start_time": "Mon, 08 Apr 2024 00:54:34 GMT",
  "state": "FINISHED",
  "status_code": 200,
  "tests_failed": 3,
  "tests_passed": 8,
  "tests_quantity": 11
}