{
  "algorithm_version": 3,
  "end_time": "Fri, 23 Feb 2024 00:08:49 GMT",
  "grade": "F",
  "hidden": false,
  "likelihood_indicator": "MEDIUM",
  "response_headers": {
    "Connection": "Keep-Alive",
    "Content-Encoding": "gzip",
    "Content-Type": "text/html;charset=UTF-8",
    "Date": "Fri, 23 Feb 2024 00:08:39 GMT",
    "Keep-Alive": "timeout=5, max=100",
    "Liferay-Portal": "Liferay Portal Community Edition 6.2 CE GA3 (Newton / Build 6202 / January 15, 2015)",
    "Server": "Apache-Coyote/1.1",
    "Set-Cookie": "JSESSIONID=93CAB86C402C52C1960FD45525E5B804; Path=/; Secure; HttpOnly, COOKIE_SUPPORT=true; Expires=Tue, 07-Oct-2070 02:50:47 GMT; Path=/; Secure; HttpOnly, GUEST_LANGUAGE_ID=es_ES; Expires=Tue, 07-Oct-2070 02:50:47 GMT; Path=/; Secure; HttpOnly, COOKIE_SUPPORT=true; Expires=Tue, 07-Oct-2070 02:50:47 GMT; Path=/; Secure; HttpOnly, GUEST_LANGUAGE_ID=es_ES; Expires=Tue, 07-Oct-2070 02:50:47 GMT; Path=/; Secure; HttpOnly, cookiesession1=678A3E26ACDEFGHIKLMNOPQSTUV0A987;Expires=Sat, 22 Feb 2025 00:08:40 GMT;Path=/;HttpOnly",
    "X-Content-Type-Options": "nosniff",
    "X-Frame-Options": "SAMEORIGIN",
    "X-XSS-Protection": "1",
    "content-length": "46100"
  },
  "scan_id": 47946020,
  "score": 0,
  "start_time": "Fri, 23 Feb 2024 00:08:37 GMT",
  "state": "FINISHED",
  "status_code": 200,
  "tests_failed": 5,
  "tests_passed": 6,
  "tests_quantity": 11
}