{
  "algorithm_version": 2,
  "end_time": "Thu, 09 Feb 2023 01:04:13 GMT",
  "grade": "F",
  "hidden": false,
  "likelihood_indicator": "MEDIUM",
  "response_headers": {
    "CF-Cache-Status": "DYNAMIC",
    "CF-RAY": "7968b081494d944a-SJC",
    "Cache-Control": "max-age=0, must-revalidate, private",
    "Connection": "keep-alive",
    "Content-Encoding": "gzip",
    "Content-Type": "text/html; charset=UTF-8",
    "Date": "Thu, 09 Feb 2023 01:04:10 GMT",
    "NEL": "{\"success_fraction\":0,\"report_to\":\"cf-nel\",\"max_age\":604800}",
    "Report-To": "{\"endpoints\":[{\"url\":\"https:\\/\\/a.nel.cloudflare.com\\/report\\/v3?s=3kqFBZHB3HCKrlnZWEFQ3AiGxyTFdpW44AftT1A1rCTA7aU2yElNff%2Bzorby%2BqqgsiZjv19myeEy5QQzYEFO%2FyUbME5mePPZL9afEfHCqmtTwNYhS0F%2Blac%2FACs6U9odLih5AWn1lPnLZVjoeD%2F15QWv6S0%3D\"}],\"group\":\"cf-nel\",\"max_age\":604800}",
    "Server": "cloudflare",
    "Transfer-Encoding": "chunked",
    "alt-svc": "h3=\":443\"; ma=86400, h3-29=\":443\"; ma=86400",
    "expires": "Thu, 09 Feb 2023 01:04:10 GMT",
    "set-cookie": "PHPSESSID=bvd8t4qjld9eb3hvfk0qtbql0f; expires=Thu, 09-Feb-2023 09:04:10 GMT; Max-Age=28800; path=/; secure; HttpOnly; SameSite=none; secure; HttpOnly; SameSite=lax",
    "x-cache": "MISS",
    "x-powered-by": "PHP/7.4.14"
  },
  "scan_id": 34052603,
  "score": 15,
  "start_time": "Thu, 09 Feb 2023 01:04:08 GMT",
  "state": "FINISHED",
  "status_code": 200,
  "tests_failed": 6,
  "tests_passed": 6,
  "tests_quantity": 12
}