{
  "algorithm_version": 2,
  "end_time": "Sat, 26 Mar 2022 00:57:20 GMT",
  "grade": "F",
  "hidden": false,
  "likelihood_indicator": "MEDIUM",
  "response_headers": {
    "Connection": "keep-alive",
    "Content-Encoding": "gzip",
    "Content-Language": "gl",
    "Content-Type": "text/html;charset=UTF-8",
    "Date": "Sat, 26 Mar 2022 00:57:02 GMT",
    "Server": "nginx",
    "Set-Cookie": "JSESSIONID=2EE61819CD173A3ABA7A892930C110FF; Path=/citaprevia; HttpOnly",
    "Transfer-Encoding": "chunked",
    "X-Frame-Options": "SAMEORIGIN",
    "X-XSS-Protection": "1; mode=block"
  },
  "scan_id": 25394209,
  "score": 10,
  "start_time": "Sat, 26 Mar 2022 00:56:57 GMT",
  "state": "FINISHED",
  "status_code": 200,
  "tests_failed": 4,
  "tests_passed": 8,
  "tests_quantity": 12
}