{
  "algorithm_version": 2,
  "end_time": "Thu, 29 Jun 2023 01:15:15 GMT",
  "grade": "F",
  "hidden": false,
  "likelihood_indicator": "MEDIUM",
  "response_headers": {
    "Cache-Control": "private, no-cache, no-store, must-revalidate",
    "Connection": "Keep-Alive",
    "Content-Length": "54332",
    "Content-Type": "text/html; charset=UTF-8",
    "Date": "Thu, 29 Jun 2023 01:15:12 GMT",
    "ETag": "\"ab5bf75\"",
    "Expires": "Thu, 01 Jan 1970 00:00:00 GMT",
    "Keep-Alive": "timeout=5, max=99",
    "Liferay-Portal": "Liferay Digital Experience Platform",
    "Pragma": "no-cache",
    "Server": "Apache",
    "Set-Cookie": "JSESSIONID=7B0Et_W4mxOc_-63SKCB9RU0oH03-zTgi6yxGwOTkGlBROqlEM1X!1850519387; path=/; HttpOnly, QueueITAccepted-SDFrts345E-V3_lmsr=EventId%3Dlmsr%26QueueId%3D6dd73afa-080e-43d0-9ba2-4b2f01e97e7e%26RedirectType%3Dsafetynet%26IssueTime%3D1688001312%26Hash%3Ddcdd9d6ad6892c61a8ef734199dd1387f95c4c922e79289bafcb43cfe945b317; expires=Fri, 30-Jun-2023 01:15:12 GMT; path=/; HttpOnly, COOKIE_SUPPORT=true; expires=Fri, 28-Jun-2024 01:15:12 GMT; path=/; secure; HttpOnly, GUEST_LANGUAGE_ID=ca_ES; domain=.gencat.cat; expires=Fri, 28-Jun-2024 01:15:12 GMT; path=/; secure; HttpOnly, COOKIE_SUPPORT=true; expires=Fri, 28-Jun-2024 01:15:12 GMT; path=/; secure; HttpOnly, QueueITAccepted-SDFrts345E-V3_lmsr=EventId%3Dlmsr%26QueueId%3D6dd73afa-080e-43d0-9ba2-4b2f01e97e7e%26RedirectType%3Dsafetynet%26IssueTime%3D1688001312%26Hash%3Ddcdd9d6ad6892c61a8ef734199dd1387f95c4c922e79289bafcb43cfe945b317; expires=Fri, 30-Jun-2023 01:15:12 GMT; path=/; HttpOnly, GUEST_LANGUAGE_ID=ca_ES; domain=.gencat.cat; expires=Fri, 28-Jun-2024 01:15:12 GMT; path=/; secure; HttpOnly",
    "X-Content-Type-Options": "nosniff",
    "X-Frame-Options": "SAMEORIGIN",
    "X-XSS-Protection": "1"
  },
  "scan_id": 39095191,
  "score": 15,
  "start_time": "Thu, 29 Jun 2023 01:14:48 GMT",
  "state": "FINISHED",
  "status_code": 200,
  "tests_failed": 3,
  "tests_passed": 9,
  "tests_quantity": 12
}