{
  "algorithm_version": 2,
  "end_time": "Thu, 05 Jan 2023 00:53:53 GMT",
  "grade": "F",
  "hidden": false,
  "likelihood_indicator": "MEDIUM",
  "response_headers": {
    "Cache-Control": "no-store, no-cache, must-revalidate",
    "Connection": "Keep-Alive",
    "Content-Encoding": "gzip",
    "Content-Type": "text/html; charset=UTF-8",
    "Date": "Thu, 05 Jan 2023 00:53:48 GMT",
    "Expires": "Thu, 19 Nov 1981 08:52:00 GMT",
    "Keep-Alive": "timeout=5, max=98",
    "Pragma": "no-cache",
    "Server": "Apache/2.4.6 (CentOS) OpenSSL/1.0.2k-fips PHP/7.4.28",
    "Set-Cookie": "PHPSESSID=fd78104be87c53560eb55f60711a8943; path=/, NSC_WT-iuuq-xfct-bcjfsubt-gjsfxbmm=wt-iuuq-nvtfpefqsfijtupsjb-ft;expires=Thu, 05-Jan-2023 00:55:48 GMT;path=/;httponly",
    "Transfer-Encoding": "chunked",
    "X-Powered-By": "PHP/7.4.28"
  },
  "scan_id": 32768652,
  "score": 0,
  "start_time": "Thu, 05 Jan 2023 00:53:46 GMT",
  "state": "FINISHED",
  "status_code": 200,
  "tests_failed": 7,
  "tests_passed": 5,
  "tests_quantity": 12
}