{
  "algorithm_version": 2,
  "end_time": "Wed, 07 Jun 2023 01:12:27 GMT",
  "grade": "F",
  "hidden": false,
  "likelihood_indicator": "MEDIUM",
  "response_headers": {
    "Alt-Svc": "h3=\":443\"; ma=2592000,h3-29=\":443\"; ma=2592000",
    "Cache-Control": "private, max-age=0",
    "Content-Encoding": "gzip",
    "Content-Type": "text/html; charset=UTF-8",
    "Date": "Wed, 07 Jun 2023 01:12:25 GMT",
    "ETag": "W/\"15fabf11effeb1b9e4d27118ab637b5a73b5c6ed276d502ab4a9ae7cfc6ace19\"",
    "Expires": "Wed, 07 Jun 2023 01:12:25 GMT",
    "Last-Modified": "Tue, 06 Jun 2023 21:54:22 GMT",
    "Server": "GSE",
    "Transfer-Encoding": "chunked",
    "X-Content-Type-Options": "nosniff",
    "X-XSS-Protection": "1; mode=block"
  },
  "scan_id": 38247300,
  "score": 0,
  "start_time": "Wed, 07 Jun 2023 01:12:22 GMT",
  "state": "FINISHED",
  "status_code": 200,
  "tests_failed": 4,
  "tests_passed": 8,
  "tests_quantity": 12
}