{
  "algorithm_version": 2,
  "end_time": "Tue, 01 Nov 2022 01:48:52 GMT",
  "grade": "F",
  "hidden": false,
  "likelihood_indicator": "MEDIUM",
  "response_headers": {
    "Access-Control-Allow-Headers": "origin, x-requested-with, content-type",
    "Access-Control-Allow-Methods": "PUT, GET, POST, DELETE, OPTIONS",
    "Cache-Control": "no-store",
    "Connection": "Keep-Alive",
    "Content-Encoding": "gzip",
    "Content-Length": "17149",
    "Content-Type": "text/html; charset=UTF-8",
    "Date": "Tue, 01 Nov 2022 01:48:20 GMT",
    "Keep-Alive": "timeout=5, max=99",
    "Last-Modified": "Tue, 01 Nov 2022 01:48:20 GMT",
    "Server": "ZENEDGE",
    "Service-Worker-Allowed": "/",
    "Set-Cookie": "SITESJSESSIONID=9kww4AlNZtXfNro860bbQ3HbNdT7vCoEyggXcMn9XqT_PVqo_bs8!614522449; path=/; HttpOnly, idioma=gl; expires=Fri, 29-Oct-2032 01:48:20 GMT; path=/, argIdioma=gl; expires=Fri, 29-Oct-2032 01:48:20 GMT; path=/, X-Oracle-BMC-LBS-Route=f0ee94706ee2ee72f2eb77e9a46b082c67a77d11ea9090b9342706c5c520eb37b830567989ed84b4; path=/; HttpOnly, X-Oracle-BMC-LBS-Route=f0ee94706ee2ee72f2eb77e9a46b082c67a77d11997bf4484161f9cf08fefda6f758c2a4e58ab304; expires=Fri, 29-Oct-2032 01:48:20 GMT; path=/, X-Oracle-BMC-LBS-Route=f0ee94706ee2ee72f2eb77e9a46b082c67a77d11997bf4484161f9cf08fefda6f758c2a4e58ab304; expires=Fri, 29-Oct-2032 01:48:20 GMT; path=/",
    "Vary": "Accept-Encoding,User-Agent",
    "Via": "1.1 sede.coruna.gal (Apache/2.4.54)",
    "X-Cache-Status": "NOTCACHED",
    "X-Cdn": "Served-By-Zenedge",
    "X-Content-Type-Options": "nosniff",
    "X-ORACLE-DMS-ECID": "0b599af3-74bd-4f63-9a96-17a12e4e9b98-002586bb",
    "X-ORACLE-DMS-RID": "0",
    "X-XSS-Protection": "1",
    "X-Zen-Fury": "bfa84bfbdf0bf9696ec5421ec2864078daa230a8",
    "device_type": "Desktop",
    "host_service": "FutureTenseContentServer:12c"
  },
  "scan_id": 30561514,
  "score": 0,
  "start_time": "Tue, 01 Nov 2022 01:48:12 GMT",
  "state": "FINISHED",
  "status_code": 200,
  "tests_failed": 5,
  "tests_passed": 7,
  "tests_quantity": 12
}