{
  "algorithm_version": 2,
  "end_time": "Tue, 25 Oct 2022 01:50:45 GMT",
  "grade": "F",
  "hidden": false,
  "likelihood_indicator": "MEDIUM",
  "response_headers": {
    "Cache-control": "no-cache, no-store, must-revalidate, max-age=0",
    "Connection": "Keep-Alive",
    "Content-encoding": "gzip",
    "Content-length": "11357",
    "Content-type": "text/html;charset=UTF-8",
    "Date": "Tue, 25 Oct 2022 01:50:35 GMT",
    "Expires": "Thu, 01 Jan 1970 00:00:00 GMT",
    "Keep-Alive": "timeout=15, max=199",
    "Last-modified": "Mon, 17 Oct 2022 10:21:32 GMT",
    "Pragma": "no-cache",
    "Server": "Servidor Web 1.0",
    "Set-cookie": "JSESSIONID=B359887DC5130C1C9FF9A19CCE2BD608.sedepropubb; Path=/; Secure; HttpOnly",
    "Vary": "Accept-Encoding",
    "X-magnolia-registration": "Registered"
  },
  "scan_id": 30364638,
  "score": 15,
  "start_time": "Tue, 25 Oct 2022 01:49:28 GMT",
  "state": "FINISHED",
  "status_code": 200,
  "tests_failed": 6,
  "tests_passed": 6,
  "tests_quantity": 12
}