{
  "algorithm_version": 2,
  "end_time": "Wed, 19 Oct 2022 01:12:51 GMT",
  "grade": "D+",
  "hidden": false,
  "likelihood_indicator": "MEDIUM",
  "response_headers": {
    "Cache-Control": "private, max-age=0",
    "Connection": "keep-alive",
    "Content-Encoding": "gzip",
    "Content-Length": "24488",
    "Content-Type": "text/html; charset=utf-8",
    "Date": "Wed, 19 Oct 2022 01:12:31 GMT",
    "Expires": "Tue, 04 Oct 2022 01:12:31 GMT",
    "Last-Modified": "Wed, 19 Oct 2022 01:12:31 GMT",
    "SPRequestGuid": "f21f09fc-6ab3-474e-b80b-69fdbc640819",
    "Set-Cookie": "ASP.NET_SessionId=kywdoc45jnin1g452it2d045; path=/; HttpOnly",
    "Strict-Transport-Security": "max-age=16070400; includeSubDomains; preload",
    "Vary": "Accept-Encoding",
    "X-FRAME-OPTIONS": "SAMEORIGIN",
    "X-MS-InvokeApp": "1; RequireReadOnly",
    "X-SharePointHealthScore": "0"
  },
  "scan_id": 30225998,
  "score": 40,
  "start_time": "Wed, 19 Oct 2022 01:12:24 GMT",
  "state": "FINISHED",
  "status_code": 200,
  "tests_failed": 6,
  "tests_passed": 6,
  "tests_quantity": 12
}