{
  "algorithm_version": 2,
  "end_time": "Sat, 10 Jun 2023 01:05:07 GMT",
  "grade": "D+",
  "hidden": false,
  "likelihood_indicator": "MEDIUM",
  "response_headers": {
    "Cache-Control": "private, max-age=0",
    "Connection": "Keep-Alive",
    "Content-Encoding": "gzip",
    "Content-Length": "21090",
    "Content-Type": "text/html; charset=utf-8",
    "Date": "Sat, 10 Jun 2023 01:04:56 GMT",
    "Expires": "Fri, 26 May 2023 01:04:56 GMT",
    "Last-Modified": "Sat, 10 Jun 2023 01:04:56 GMT",
    "SPRequestGuid": "a985e22d-062e-410c-8c0a-75dfb4c71473",
    "Set-Cookie": "ASP.NET_SessionId=xr21hm55r2ycgf55j2i1qwmp; path=/; HttpOnly",
    "Strict-Transport-Security": "max-age=16070400; includeSubDomains; preload",
    "Vary": "Accept-Encoding",
    "X-FRAME-OPTIONS": "SAMEORIGIN",
    "X-MS-InvokeApp": "1; RequireReadOnly",
    "X-SharePointHealthScore": "0"
  },
  "scan_id": 38343612,
  "score": 40,
  "start_time": "Sat, 10 Jun 2023 01:04:48 GMT",
  "state": "FINISHED",
  "status_code": 200,
  "tests_failed": 6,
  "tests_passed": 6,
  "tests_quantity": 12
}