{
  "algorithm_version": 2,
  "end_time": "Sat, 27 Jan 2024 00:41:05 GMT",
  "grade": "C-",
  "hidden": false,
  "likelihood_indicator": "MEDIUM",
  "response_headers": {
    "Cache-Control": "private, max-age=0",
    "Connection": "Keep-Alive",
    "Content-Encoding": "gzip",
    "Content-Length": "27047",
    "Content-Type": "text/html; charset=utf-8",
    "Date": "Sat, 27 Jan 2024 00:40:43 GMT",
    "Expires": "Fri, 12 Jan 2024 00:40:43 GMT",
    "Last-Modified": "Sat, 27 Jan 2024 00:40:43 GMT",
    "SPIisLatency": "0",
    "SPRequestDuration": "843",
    "SPRequestGuid": "96a805a1-2bb0-6082-6e4d-cf06b1c564a0",
    "Set-Cookie": "ASP.NET_SessionId=tesw42mgbnoartqdknfszjkg; path=/; HttpOnly; SameSite=Lax",
    "Strict-Transport-Security": "max-age=16070400; includeSubDomains; preload",
    "Vary": "Accept-Encoding",
    "X-Content-Type-Options": "nosniff",
    "X-FRAME-OPTIONS": "SAMEORIGIN",
    "X-MS-InvokeApp": "1; RequireReadOnly",
    "X-SharePointHealthScore": "0",
    "request-id": "96a805a1-2bb0-6082-6e4d-cf06b1c564a0"
  },
  "scan_id": 47096234,
  "score": 45,
  "start_time": "Sat, 27 Jan 2024 00:40:33 GMT",
  "state": "FINISHED",
  "status_code": 200,
  "tests_failed": 5,
  "tests_passed": 7,
  "tests_quantity": 12
}