{
  "algorithm_version": 2,
  "end_time": "Tue, 30 Aug 2022 01:14:10 GMT",
  "grade": "B",
  "hidden": false,
  "likelihood_indicator": "MEDIUM",
  "response_headers": {
    "Accept-Ranges": "bytes",
    "Access-Control-Allow-Credentials": "true",
    "Cache-Control": "max-age=14400",
    "Connection": "Keep-Alive",
    "Content-Language": "es-ES",
    "Content-Length": "61088",
    "Content-Security-Policy": "frame-ancestors 'self' *.agenciatributaria.gob.es",
    "Content-Type": "text/html",
    "Date": "Tue, 30 Aug 2022 01:14:07 GMT",
    "ETag": "\"478917-eea0-5e75fc29b9103\"",
    "Expires": "Tue, 30 Aug 2022 05:14:07 GMT",
    "Keep-Alive": "timeout=20, max=200",
    "Last-Modified": "Mon, 29 Aug 2022 11:42:36 GMT",
    "Strict-Transport-Security": "max-age=31536000; includeSubDomains",
    "Vary": "origin",
    "X-XSS-Protection": "1; mode=block",
    "x-site": "Sede"
  },
  "scan_id": 29043993,
  "score": 75,
  "start_time": "Tue, 30 Aug 2022 01:13:16 GMT",
  "state": "FINISHED",
  "status_code": 200,
  "tests_failed": 2,
  "tests_passed": 10,
  "tests_quantity": 12
}