{
  "algorithm_version": 3,
  "end_time": "Sat, 29 Jun 2024 00:58:34 GMT",
  "grade": "F",
  "hidden": false,
  "likelihood_indicator": "MEDIUM",
  "response_headers": {
    "Accept-Ranges": "bytes",
    "Access-Control-Allow-Origin": "*",
    "Age": "25218031",
    "Cache-Control": "s-maxage=120, public",
    "Connection": "keep-alive",
    "Content-Length": "455",
    "Content-Type": "text/html; charset=UTF-8",
    "Date": "Mon, 11 Sep 2023 03:58:00 GMT",
    "ETag": "W/\"455-1490177218000\"",
    "Last-Modified": "Wed, 22 Mar 2017 10:06:58 GMT",
    "Server": "Apache-Coyote/1.1",
    "Via": "1.1 f9cbfbc3568832d017c09dbd4649932c.cloudfront.net (CloudFront)",
    "X-Amz-Cf-Id": "ZX5Wr1zolsNQQAkN6bISaA_zLWshM7PYh-LxoLD8d9lrAinDWkjHNA==",
    "X-Amz-Cf-Pop": "HIO52-P2",
    "X-Cache": "Hit from cloudfront"
  },
  "scan_id": 52824162,
  "score": 0,
  "start_time": "Sat, 29 Jun 2024 00:58:31 GMT",
  "state": "FINISHED",
  "status_code": 200,
  "tests_failed": 6,
  "tests_passed": 5,
  "tests_quantity": 11
}