{
  "algorithm_version": 2,
  "end_time": "Sun, 27 Mar 2022 01:01:44 GMT",
  "grade": "F",
  "hidden": false,
  "likelihood_indicator": "MEDIUM",
  "response_headers": {
    "Cache-Control": "private, max-age=0",
    "Connection": "keep-alive",
    "Content-Length": "63552",
    "Content-Type": "text/html; charset=utf-8",
    "Date": "Sun, 27 Mar 2022 01:01:21 GMT",
    "Expires": "Sat, 12 Mar 2022 02:01:20 GMT",
    "Last-Modified": "Sun, 27 Mar 2022 01:01:20 GMT",
    "MicrosoftSharePointTeamServices": "16.0.0.5095",
    "SPIisLatency": "0",
    "SPRequestDuration": "1332",
    "SPRequestGuid": "12b12da0-2788-20d8-a8e3-7169dcc8746d",
    "Server": "Microsoft-IIS/10.0",
    "X-AspNet-Version": "4.0.30319",
    "X-Content-Type-Options": "nosniff",
    "X-FRAME-OPTIONS": "SAMEORIGIN",
    "X-MS-InvokeApp": "1; RequireReadOnly",
    "X-Powered-By": "ASP.NET",
    "X-SharePointHealthScore": "0",
    "request-id": "12b12da0-2788-20d8-a8e3-7169dcc8746d"
  },
  "scan_id": 25406931,
  "score": 20,
  "start_time": "Sun, 27 Mar 2022 01:01:14 GMT",
  "state": "FINISHED",
  "status_code": 200,
  "tests_failed": 5,
  "tests_passed": 7,
  "tests_quantity": 12
}