{
  "algorithm_version": 2,
  "end_time": "Mon, 30 Oct 2023 00:11:17 GMT",
  "grade": "F",
  "hidden": false,
  "likelihood_indicator": "MEDIUM",
  "response_headers": {
    "Cache-Control": "no-store, max-age=0",
    "Connection": "keep-alive",
    "Content-Length": "2053",
    "Content-Type": "text/html; charset=UTF-8",
    "Date": "Mon, 30 Oct 2023 00:11:16 GMT",
    "Server": "CloudFront",
    "Via": "1.1 d9fe97589e952f97209f7a422c89d876.cloudfront.net (CloudFront)",
    "X-Amz-Cf-Id": "WgjJNEF-tV_ymjiLpOoV8GlGR2LwdxB5nHwOdvVuSDZx9ByivSDmBg==",
    "X-Amz-Cf-Pop": "DEN52-P2",
    "X-Cache": "Error from cloudfront",
    "x-amzn-waf-action": "captcha"
  },
  "scan_id": 43781655,
  "score": 15,
  "start_time": "Mon, 30 Oct 2023 00:11:15 GMT",
  "state": "FINISHED",
  "status_code": 405,
  "tests_failed": 6,
  "tests_passed": 6,
  "tests_quantity": 12
}