{
  "algorithm_version": 2,
  "end_time": "Tue, 07 Feb 2023 01:03:56 GMT",
  "grade": "B-",
  "hidden": false,
  "likelihood_indicator": "MEDIUM",
  "response_headers": {
    "Cache-Control": "no-cache",
    "Content-Encoding": "gzip",
    "Content-Length": "16136",
    "Content-Type": "text/html; charset=utf-8",
    "Date": "Tue, 07 Feb 2023 01:03:52 GMT",
    "Expires": "-1",
    "Pragma": "no-cache",
    "SPIisLatency": "0",
    "SPRequestDuration": "1297",
    "SPRequestGuid": "36b993a0-f204-b025-e01d-c6431c4da801",
    "Server": "Microsoft-IIS/8.0",
    "Set-Cookie": "lang=es; Expires=Mon, 07-Feb-2033 01:03:50 GMT; Path=/; Secure; HttpOnly",
    "Strict-Transport-Security": "max-age=31536000; includeSubDomains; preload",
    "Vary": "Accept-Encoding",
    "X-AspNet-Version": "4.0.30319",
    "X-Content-Type-Options": "nosniff",
    "X-FRAME-OPTIONS": "SAMEORIGIN",
    "X-MS-InvokeApp": "1; RequireReadOnly",
    "X-Powered-By": "ASP.NET",
    "X-SharePointHealthScore": "0",
    "request-id": "36b993a0-f204-b025-e01d-c6431c4da801"
  },
  "scan_id": 33954552,
  "score": 65,
  "start_time": "Tue, 07 Feb 2023 01:03:46 GMT",
  "state": "FINISHED",
  "status_code": 200,
  "tests_failed": 2,
  "tests_passed": 10,
  "tests_quantity": 12
}