{
  "algorithm_version": 2,
  "end_time": "Wed, 15 Nov 2023 00:55:50 GMT",
  "grade": "F",
  "hidden": false,
  "likelihood_indicator": "MEDIUM",
  "response_headers": {
    "Cache-Control": "no-cache=\"Set-Cookie,Set-Cookie\"",
    "Content-Type": "text/html; charset=UTF-8",
    "Date": "Wed, 15 Nov 2023 00:55:33 GMT",
    "Last-Modified": "Wed, 15 Nov 2023 00:55:34 GMT",
    "Set-Cookie": "JSESSIONID=SMDQee6Ug05ieMcLnuFF_HrZ8Vbod5mxyBXjDAqRe2QSyVqTqnx9!-1587739711!-1785638577; path=/, SS_X_JSESSIONID=eFvQee6mbQVx8dOrrBYNVrwpHbWVjeKIOGCkLFCdyi9kRYXhUMKh!-1188773594!1855265467; path=/; secure; HttpOnly, TS0101df13=01301e525b91831228e166f764f77eda618728674c9fb5012593a10cec23b76d3a15e001cdbb59f69dadb08a0b892a9db63f9bd228; Path=/; Domain=.enaire.es",
    "Transfer-Encoding": "chunked",
    "X-Cnection": "close",
    "X-ORACLE-DMS-ECID": "d44f8690-f75e-4bdc-81a8-b2c96043f910-00015232, 2706efbb-32e7-48d4-9b74-ff9c73f6394e-000dac3f",
    "X-ORACLE-DMS-RID": "0, 0",
    "device_type": "Any",
    "x-content-type-options": "nosniff",
    "x-xss-protection": "1"
  },
  "scan_id": 44434400,
  "score": 0,
  "start_time": "Wed, 15 Nov 2023 00:55:23 GMT",
  "state": "FINISHED",
  "status_code": 200,
  "tests_failed": 5,
  "tests_passed": 7,
  "tests_quantity": 12
}