{
  "algorithm_version": 2,
  "end_time": "Fri, 01 Jul 2022 01:05:23 GMT",
  "grade": "F",
  "hidden": false,
  "likelihood_indicator": "MEDIUM",
  "response_headers": {
    "Accept-Ranges": "bytes",
    "Age": "3",
    "Cache-Control": "max-age=0",
    "Connection": "keep-alive",
    "Content-Length": "0",
    "Content-Type": "text/html; charset=UTF-8",
    "Date": "Fri, 01 Jul 2022 01:05:20 GMT",
    "Expires": "Fri, 01 Jul 2022 01:05:15 GMT",
    "Server": "HTTPd",
    "Vary": "Accept-Encoding"
  },
  "scan_id": 27514186,
  "score": 0,
  "start_time": "Fri, 01 Jul 2022 01:05:11 GMT",
  "state": "FINISHED",
  "status_code": 200,
  "tests_failed": 6,
  "tests_passed": 6,
  "tests_quantity": 12
}