{
  "algorithm_version": 2,
  "end_time": "Tue, 01 Mar 2022 01:09:25 GMT",
  "grade": "F",
  "hidden": false,
  "likelihood_indicator": "MEDIUM",
  "response_headers": {
    "Accept-ranges": "bytes",
    "Cache-control": "public,max-age=300",
    "Content-length": "57306",
    "Content-type": "text/html",
    "Date": "Tue, 01 Mar 2022 01:09:21 GMT",
    "Etag": "\"dfda-6209fdf9\"",
    "Last-modified": "Mon, 14 Feb 2022 07:00:09 GMT",
    "Server": "Servidor-Web"
  },
  "scan_id": 24838328,
  "score": 15,
  "start_time": "Tue, 01 Mar 2022 01:09:16 GMT",
  "state": "FINISHED",
  "status_code": 200,
  "tests_failed": 6,
  "tests_passed": 6,
  "tests_quantity": 12
}