{
  "algorithm_version": 2,
  "end_time": "Wed, 11 Jan 2023 01:04:26 GMT",
  "grade": "F",
  "hidden": false,
  "likelihood_indicator": "MEDIUM",
  "response_headers": {
    "Cache-Control": "private, max-age=0",
    "Content-Encoding": "gzip",
    "Content-Length": "23657",
    "Content-Type": "text/html; charset=utf-8",
    "Date": "Wed, 11 Jan 2023 01:04:01 GMT",
    "Expires": "Tue, 27 Dec 2022 01:04:02 GMT",
    "Last-Modified": "Wed, 11 Jan 2023 01:04:02 GMT",
    "MicrosoftSharePointTeamServices": "15.0.0.4945",
    "SPIisLatency": "0",
    "SPRequestDuration": "137",
    "SPRequestGuid": "7d088ba0-4c86-d0ec-52de-290bbf283f3b",
    "Server": "Microsoft-IIS/8.5",
    "Vary": "Accept-Encoding",
    "X-AspNet-Version": "4.0.30319",
    "X-Content-Type-Options": "nosniff",
    "X-FRAME-OPTIONS": "SAMEORIGIN",
    "X-MS-InvokeApp": "1; RequireReadOnly",
    "X-Powered-By": "ASP.NET",
    "X-SharePointHealthScore": "0",
    "request-id": "7d088ba0-4c86-d0ec-52de-290bbf283f3b"
  },
  "scan_id": 33009300,
  "score": 0,
  "start_time": "Wed, 11 Jan 2023 01:03:57 GMT",
  "state": "FINISHED",
  "status_code": 200,
  "tests_failed": 4,
  "tests_passed": 8,
  "tests_quantity": 12
}