{
  "algorithm_version": 2,
  "end_time": "Sat, 30 Dec 2023 00:57:44 GMT",
  "grade": "F",
  "hidden": false,
  "likelihood_indicator": "MEDIUM",
  "response_headers": {
    "Cache-Control": "public, max-age=0",
    "Connection": "Keep-Alive",
    "Content-Length": "167681",
    "Content-Type": "text/html;charset=UTF-8",
    "Date": "Sat, 30 Dec 2023 00:57:36 GMT",
    "Last-Modified": "Sat, 30 Dec 2023 00:57:36 GMT",
    "Server": "OpenCms/11.0.1",
    "Set-Cookie": "JSESSIONID=3B2657186D145D1DD52942FFB1F85F59.NodoPortal1; Path=/; Secure; HttpOnly",
    "X-XSS-Protection": "1; mode=block"
  },
  "scan_id": 45962892,
  "score": 5,
  "start_time": "Sat, 30 Dec 2023 00:52:59 GMT",
  "state": "FINISHED",
  "status_code": 200,
  "tests_failed": 6,
  "tests_passed": 6,
  "tests_quantity": 12
}