{
  "algorithm_version": 2,
  "end_time": "Mon, 24 Oct 2022 01:28:18 GMT",
  "grade": "F",
  "hidden": false,
  "likelihood_indicator": "MEDIUM",
  "response_headers": {
    "Cache-Control": "public, max-age=10800",
    "Connection": "close",
    "Content-Encoding": "gzip",
    "Content-Language": "es",
    "Content-Length": "18714",
    "Content-Type": "text/html; charset=utf-8",
    "Date": "Mon, 24 Oct 2022 01:26:51 GMT",
    "Etag": "\"1666574811-1\"",
    "Expires": "Sun, 19 Nov 1978 05:00:00 GMT",
    "Last-Modified": "Mon, 24 Oct 2022 01:26:51 GMT",
    "Server": "Apache",
    "Vary": "Cookie,Accept-Encoding",
    "X-Content-Type-Options": "nosniff",
    "X-Frame-Options": "SAMEORIGIN"
  },
  "scan_id": 30337870,
  "score": 0,
  "start_time": "Mon, 24 Oct 2022 01:26:54 GMT",
  "state": "FINISHED",
  "status_code": 200,
  "tests_failed": 4,
  "tests_passed": 8,
  "tests_quantity": 12
}