{
  "algorithm_version": 3,
  "end_time": "Thu, 13 Jun 2024 00:13:11 GMT",
  "grade": "F",
  "hidden": false,
  "likelihood_indicator": "MEDIUM",
  "response_headers": {
    "Connection": "Keep-Alive",
    "Content-Encoding": "gzip",
    "Content-Length": "48424",
    "Content-Type": "text/html; charset=UTF-8",
    "Date": "Thu, 13 Jun 2024 00:12:53 GMT",
    "Keep-Alive": "timeout=5, max=100",
    "Link": "<https://www.museoycircuitofernandoalonso.com/wp-json/>; rel=\"https://api.w.org/\", <https://www.museoycircuitofernandoalonso.com/wp-json/wp/v2/pages/92>; rel=\"alternate\"; type=\"application/json\", <https://www.museoycircuitofernandoalonso.com/>; rel=shortlink",
    "Server": "Apache",
    "Set-Cookie": "wp_wpfileupload_25d05f10cb23f61309713ce94fd5f8c1=dg9T8tSkH7yNWg91Mc7F43GTR8C8j2WM; expires=Sat, 15-Jun-2024 00:12:53 GMT; Max-Age=172800; path=/",
    "Vary": "Accept-Encoding",
    "X-UA-Compatible": "IE=edge"
  },
  "scan_id": 52208247,
  "score": 5,
  "start_time": "Thu, 13 Jun 2024 00:12:48 GMT",
  "state": "FINISHED",
  "status_code": 200,
  "tests_failed": 6,
  "tests_passed": 5,
  "tests_quantity": 11
}