{
  "algorithm_version": 3,
  "end_time": "Mon, 24 Jun 2024 01:00:50 GMT",
  "grade": "F",
  "hidden": false,
  "likelihood_indicator": "MEDIUM",
  "response_headers": {
    "Connection": "Keep-Alive",
    "Content-Encoding": "gzip",
    "Content-Length": "7826",
    "Content-Type": "text/html;charset=ISO-8859-1",
    "Date": "Mon, 24 Jun 2024 01:00:49 GMT",
    "Keep-Alive": "timeout=5, max=100",
    "Server": "Apache",
    "Set-Cookie": "JSESSIONID=21D301FAF8293351F99A04947A7A195A; Path=/; HttpOnly, cookiesession1=678A3E5E7C3AC14F43A71B80F73C2738;Expires=Tue, 24 Jun 2025 01:00:49 GMT;Path=/;HttpOnly",
    "Vary": "Accept-Encoding"
  },
  "scan_id": 52625064,
  "score": 0,
  "start_time": "Mon, 24 Jun 2024 01:00:46 GMT",
  "state": "FINISHED",
  "status_code": 200,
  "tests_failed": 7,
  "tests_passed": 4,
  "tests_quantity": 11
}