{
  "algorithm_version": 3,
  "end_time": "Mon, 19 Feb 2024 00:09:25 GMT",
  "grade": "F",
  "hidden": false,
  "likelihood_indicator": "MEDIUM",
  "response_headers": {
    "Connection": "Keep-Alive",
    "Content-Encoding": "gzip",
    "Content-Length": "17114",
    "Content-Type": "text/html; charset=UTF-8",
    "Date": "Mon, 19 Feb 2024 00:09:22 GMT",
    "ETag": "\"557dfd06\"",
    "Keep-Alive": "timeout=5, max=100",
    "Liferay-Portal": "Liferay Portal Community Edition 6.2 CE GA3 (Newton / Build 6202 / January 15, 2015)",
    "Server": "Apache-Coyote/1.1",
    "Set-Cookie": "JSESSIONID=B2D25734FCC087EF2F14F1E3CF79BA8C; Path=/; Secure; HttpOnly, COOKIE_SUPPORT=true; Expires=Fri, 03-Oct-2070 02:51:30 GMT; Path=/; Secure; HttpOnly, GUEST_LANGUAGE_ID=es_ES; Expires=Fri, 03-Oct-2070 02:51:30 GMT; Path=/; Secure; HttpOnly, COOKIE_SUPPORT=true; Expires=Fri, 03-Oct-2070 02:51:30 GMT; Path=/; Secure; HttpOnly, GUEST_LANGUAGE_ID=es_ES; Expires=Fri, 03-Oct-2070 02:51:30 GMT; Path=/; Secure; HttpOnly, COOKIE_SUPPORT=true; Expires=Fri, 03-Oct-2070 02:51:30 GMT; Path=/; Secure; HttpOnly, GUEST_LANGUAGE_ID=es_ES; Expires=Fri, 03-Oct-2070 02:51:30 GMT; Path=/; Secure; HttpOnly, cookiesession1=678A3E25TVWXYZABCEFGHIJKMNOPEC1B;Expires=Tue, 18 Feb 2025 00:09:22 GMT;Path=/;HttpOnly",
    "X-Content-Type-Options": "nosniff",
    "X-Frame-Options": "SAMEORIGIN",
    "X-XSS-Protection": "1"
  },
  "scan_id": 47783014,
  "score": 10,
  "start_time": "Mon, 19 Feb 2024 00:09:16 GMT",
  "state": "FINISHED",
  "status_code": 200,
  "tests_failed": 4,
  "tests_passed": 7,
  "tests_quantity": 11
}