{
  "algorithm_version": 2,
  "end_time": "Sat, 25 Jun 2022 01:14:19 GMT",
  "grade": "F",
  "hidden": false,
  "likelihood_indicator": "MEDIUM",
  "response_headers": {
    "Cache-Control": "no-cache, no-store",
    "Connection": "keep-alive",
    "Content-Length": "786404",
    "Content-Type": "text/html; charset=utf-8",
    "Date": "Sat, 25 Jun 2022 01:13:55 GMT",
    "Expires": "-1",
    "Pragma": "no-cache",
    "Server": "Microsoft-IIS/10.0",
    "Set-Cookie": "ASP.NET_SessionId=r0geqsb2jnjyab3cufsrsywh; path=/; HttpOnly; SameSite=Lax, SC_ANALYTICS_GLOBAL_COOKIE=637ff83b96624a9d874edb9b8ed86b55|False; expires=Tue, 22-Jun-2032 01:13:54 GMT; path=/; HttpOnly, ARRAffinity=53f4a96b1c4fe0ee3118f9ad5503cc06fc63377ccfde033e0776e5f7ac42f04d;Path=/;HttpOnly;Secure;Domain=www.webtenerife.com, ARRAffinitySameSite=53f4a96b1c4fe0ee3118f9ad5503cc06fc63377ccfde033e0776e5f7ac42f04d;Path=/;HttpOnly;SameSite=None;Secure;Domain=www.webtenerife.com"
  },
  "scan_id": 27382757,
  "score": 0,
  "start_time": "Sat, 25 Jun 2022 01:13:48 GMT",
  "state": "FINISHED",
  "status_code": 200,
  "tests_failed": 8,
  "tests_passed": 4,
  "tests_quantity": 12
}