{
  "algorithm_version": 2,
  "end_time": "Thu, 23 Feb 2023 01:04:15 GMT",
  "grade": "B-",
  "hidden": false,
  "likelihood_indicator": "MEDIUM",
  "response_headers": {
    "Cache-Control": "no-cache",
    "Content-Encoding": "gzip",
    "Content-Length": "15129",
    "Content-Type": "text/html; charset=utf-8",
    "Date": "Thu, 23 Feb 2023 01:04:00 GMT",
    "Expires": "-1",
    "Pragma": "no-cache",
    "SPIisLatency": "0",
    "SPRequestDuration": "1659",
    "SPRequestGuid": "94df98a0-d236-b025-515a-3792875ac07e",
    "Server": "Microsoft-IIS/8.0",
    "Set-Cookie": "lang=es; Expires=Wed, 23-Feb-2033 01:03:59 GMT; Path=/; Secure; HttpOnly",
    "Strict-Transport-Security": "max-age=31536000; includeSubDomains; preload",
    "Vary": "Accept-Encoding",
    "X-AspNet-Version": "4.0.30319",
    "X-Content-Type-Options": "nosniff",
    "X-FRAME-OPTIONS": "SAMEORIGIN",
    "X-MS-InvokeApp": "1; RequireReadOnly",
    "X-Powered-By": "ASP.NET",
    "X-SharePointHealthScore": "0",
    "request-id": "94df98a0-d236-b025-515a-3792875ac07e"
  },
  "scan_id": 34619471,
  "score": 65,
  "start_time": "Thu, 23 Feb 2023 01:03:53 GMT",
  "state": "FINISHED",
  "status_code": 200,
  "tests_failed": 2,
  "tests_passed": 10,
  "tests_quantity": 12
}