{
  "algorithm_version": 2,
  "end_time": "Sat, 10 Sep 2022 01:43:34 GMT",
  "grade": "F",
  "hidden": false,
  "likelihood_indicator": "MEDIUM",
  "response_headers": {
    "Cache-Control": "no-cache, no-store",
    "Content-Length": "114879",
    "Content-Type": "text/html; charset=utf-8",
    "Date": "Sat, 10 Sep 2022 01:43:22 GMT",
    "Expires": "-1",
    "Pragma": "no-cache",
    "Server": "Microsoft-IIS/10.0",
    "Set-Cookie": "ASP.NET_SessionId=4nbki3mk4kf2er4nf25z41dk; path=/; HttpOnly; SameSite=Lax, sto-id-47873=EOCABEKMFAAA; Path=/"
  },
  "scan_id": 29296244,
  "score": 0,
  "start_time": "Sat, 10 Sep 2022 01:43:18 GMT",
  "state": "FINISHED",
  "status_code": 200,
  "tests_failed": 6,
  "tests_passed": 6,
  "tests_quantity": 12
}