{
  "algorithm_version": 2,
  "end_time": "Wed, 11 Oct 2023 00:08:58 GMT",
  "grade": "F",
  "hidden": false,
  "likelihood_indicator": "MEDIUM",
  "response_headers": {
    "Cache-Control": "public, max-age=0",
    "Connection": "Keep-Alive",
    "Content-Encoding": "gzip",
    "Content-Type": "text/html;charset=UTF-8",
    "Date": "Wed, 11 Oct 2023 00:08:53 GMT",
    "Keep-Alive": "timeout=5, max=100",
    "Last-Modified": "Tue, 10 Oct 2023 17:08:53 PDT",
    "Server": "OpenCms/10.5.x",
    "Set-Cookie": "JSESSIONID=BD32EF970AEB28D6BD3B20D07AA773E4; Path=/; Secure; HttpOnly",
    "Transfer-Encoding": "chunked",
    "Vary": "Accept-Encoding"
  },
  "scan_id": 43103584,
  "score": 0,
  "start_time": "Wed, 11 Oct 2023 00:08:25 GMT",
  "state": "FINISHED",
  "status_code": 200,
  "tests_failed": 6,
  "tests_passed": 6,
  "tests_quantity": 12
}