{
  "algorithm_version": 2,
  "end_time": "Thu, 23 Jun 2022 14:31:06 GMT",
  "grade": "D+",
  "hidden": true,
  "likelihood_indicator": "MEDIUM",
  "response_headers": {
    "Cache-Control": "no-store, no-cache, must-revalidate, post-check=0, pre-check=0",
    "Connection": "Keep-Alive",
    "Content-Encoding": "gzip",
    "Content-Security-Policy": "default-src https: data:; style-src 'self' 'unsafe-inline' https:; object-src 'self'; script-src * 'unsafe-inline' 'unsafe-eval' https:; img-src 'self' https: data:; frame-src *; frame-ancestors 'self'; base-uri 'self'; form-action *",
    "Content-Type": "text/html; charset=utf-8",
    "Date": "Thu, 23 Jun 2022 14:31:01 GMT",
    "Expires": "Wed, 17 Aug 2005 00:00:00 GMT",
    "Keep-Alive": "timeout=15, max=100",
    "Last-Modified": "Thu, 23 Jun 2022 14:31:01 GMT",
    "P3P": "CP=\"NOI ADM DEV PSAi COM NAV OUR OTRo STP IND DEM\"",
    "Permissions-Policy": "interest-cohort=()",
    "Pragma": "no-cache",
    "Referrer-Policy": "no-referrer",
    "Server": "XXXXXXX",
    "Set-Cookie": "ff2850209f5e40085fb78ce3df7d39da=41m0oljcs3vjkgjlodjf7cjgk0; path=/; HttpOnly;HttpOnly;Secure;SameSite=None;Max-Age=7200, cookiesession1=678A3E1198901234ABCDEFHIJKLM215D;Expires=Fri, 23 Jun 2023 14:31:01 GMT;Path=/;Secure;HttpOnly;SameSite=None, visid_incap_1560598=hUqJH0DRTf6UoZoj2vR/XCN5tGIAAAAAQUIPAAAAAACL9AQ7nUgAj1NOoRF9m+L1; expires=Fri, 23 Jun 2023 06:16:40 GMT; HttpOnly; path=/; Domain=.ccn-cert.cni.es; Secure; SameSite=None, incap_ses_133_1560598=A/m/cdtlNTLnucg3FoPYASV5tGIAAAAAl2pUo+DUZ6af9ROrBLXc/A==; path=/; Domain=.ccn-cert.cni.es; Secure; SameSite=None",
    "Strict-Transport-Security": "max-age=31536000; includeSubDomains",
    "Transfer-Encoding": "chunked",
    "Vary": "Accept-Encoding",
    "X-CDN": "Imperva",
    "X-Content-Type-Options": "nosniff",
    "X-Frame-Options": "SAMEORIGIN",
    "X-Iinfo": "10-138253558-138253564 NNNN CT(167 168 0) RT(1655994660415 42) q(0 0 3 0) r(5 8) U12",
    "X-XSS-Protection": "1; mode=block"
  },
  "scan_id": 27353515,
  "score": 40,
  "start_time": "Thu, 23 Jun 2022 14:30:57 GMT",
  "state": "FINISHED",
  "status_code": 200,
  "tests_failed": 3,
  "tests_passed": 9,
  "tests_quantity": 12
}