{
  "algorithm_version": 2,
  "end_time": "Fri, 30 Dec 2022 01:02:46 GMT",
  "grade": "F",
  "hidden": false,
  "likelihood_indicator": "MEDIUM",
  "response_headers": {
    "Cache-Control": "private, max-age=0",
    "Connection": "keep-alive",
    "Content-Length": "67046",
    "Content-Type": "text/html; charset=utf-8",
    "Date": "Fri, 30 Dec 2022 01:02:35 GMT",
    "Expires": "Thu, 15 Dec 2022 01:02:34 GMT",
    "Last-Modified": "Fri, 30 Dec 2022 01:02:34 GMT",
    "MicrosoftSharePointTeamServices": "16.0.0.5095",
    "SPIisLatency": "0",
    "SPRequestDuration": "1096",
    "SPRequestGuid": "a32b87a0-070c-20d8-a8e3-7531d4b636c8",
    "Server": "Microsoft-IIS/10.0",
    "X-AspNet-Version": "4.0.30319",
    "X-Content-Type-Options": "nosniff",
    "X-FRAME-OPTIONS": "SAMEORIGIN",
    "X-MS-InvokeApp": "1; RequireReadOnly",
    "X-Powered-By": "ASP.NET",
    "X-SharePointHealthScore": "0",
    "request-id": "a32b87a0-070c-20d8-a8e3-7531d4b636c8"
  },
  "scan_id": 32530765,
  "score": 20,
  "start_time": "Fri, 30 Dec 2022 01:02:29 GMT",
  "state": "FINISHED",
  "status_code": 200,
  "tests_failed": 5,
  "tests_passed": 7,
  "tests_quantity": 12
}