{
  "algorithm_version": 2,
  "end_time": "Mon, 12 Sep 2022 00:13:54 GMT",
  "grade": "D",
  "hidden": false,
  "likelihood_indicator": "MEDIUM",
  "response_headers": {
    "Accept-Ranges": "bytes",
    "Connection": "Upgrade, Keep-Alive",
    "Content-Encoding": "gzip",
    "Content-Type": "text/html",
    "Date": "Mon, 12 Sep 2022 00:13:52 GMT",
    "Keep-Alive": "timeout=15, max=100",
    "Last-Modified": "Mon, 18 Apr 2022 07:48:09 GMT",
    "Referrer-Policy": "no-referrer-when-downgrade",
    "Set-Cookie": "nlbi_171420=ErxoeY9tOFUmYreP3tof+wAAAABQdXLSj8LbJ72nrceyBJ5A; path=/; Domain=.grancanaria.com; Secure; SameSite=None, visid_incap_171420=1TPFFLsYR6St/7nMwtjACb95HmMAAAAAQUIPAAAAAACMfTgkOXB5OiP668AZYntN; expires=Mon, 11 Sep 2023 06:49:19 GMT; HttpOnly; path=/; Domain=.grancanaria.com; Secure; SameSite=None, incap_ses_257_171420=kwZLZWzmS1a1GRGbcgyRA8B5HmMAAAAAmLgf04b4qp5O9KlQz6vwtw==; path=/; Domain=.grancanaria.com; Secure; SameSite=None",
    "Strict-Transport-Security": "max-age=31536000",
    "Transfer-Encoding": "chunked",
    "Upgrade": "h2",
    "Vary": "Accept-Encoding",
    "X-CDN": "Imperva",
    "X-Content-Type-Options": "nosniff",
    "X-Frame-Options": "SAMEORIGIN",
    "X-Iinfo": "5-10754027-10746858 pNNN RT(1662941631981 22) q(0 0 0 14) r(2 2) U12",
    "X-XSS-Protection": "1; mode=block"
  },
  "scan_id": 29330283,
  "score": 30,
  "start_time": "Mon, 12 Sep 2022 00:13:50 GMT",
  "state": "FINISHED",
  "status_code": 200,
  "tests_failed": 4,
  "tests_passed": 8,
  "tests_quantity": 12
}