{
  "algorithm_version": 2,
  "end_time": "Fri, 11 Nov 2022 01:04:43 GMT",
  "grade": "F",
  "hidden": false,
  "likelihood_indicator": "MEDIUM",
  "response_headers": {
    "Accept-ranges": "bytes",
    "Cache-control": "public,max-age=300",
    "Content-length": "46928",
    "Content-type": "text/html",
    "Date": "Fri, 11 Nov 2022 01:04:08 GMT",
    "Etag": "\"b750-636a805a\"",
    "Last-modified": "Tue, 08 Nov 2022 16:14:18 GMT",
    "Server": "Servidor-Web"
  },
  "scan_id": 30823292,
  "score": 15,
  "start_time": "Fri, 11 Nov 2022 01:02:53 GMT",
  "state": "FINISHED",
  "status_code": 200,
  "tests_failed": 6,
  "tests_passed": 6,
  "tests_quantity": 12
}