{
  "algorithm_version": 2,
  "end_time": "Sat, 01 Apr 2023 01:02:08 GMT",
  "grade": "F",
  "hidden": false,
  "likelihood_indicator": "MEDIUM",
  "response_headers": {
    "CF-Cache-Status": "DYNAMIC",
    "CF-RAY": "7b0ce6633fa5d049-SJC",
    "Cache-Control": "no-store, no-cache, must-revalidate",
    "Connection": "keep-alive",
    "Content-Encoding": "gzip",
    "Content-Type": "text/html; charset=UTF-8",
    "Date": "Sat, 01 Apr 2023 01:01:19 GMT",
    "Expires": "Thu, 19 Nov 1981 08:52:00 GMT",
    "Link": "<https://www.fgc.cat/wp-json/>; rel=\"https://api.w.org/\", <https://www.fgc.cat/wp-json/wp/v2/pages/5>; rel=\"alternate\"; type=\"application/json\", <https://www.fgc.cat/>; rel=shortlink",
    "NEL": "{\"success_fraction\":0,\"report_to\":\"cf-nel\",\"max_age\":604800}",
    "Pragma": "no-cache",
    "Report-To": "{\"endpoints\":[{\"url\":\"https:\\/\\/a.nel.cloudflare.com\\/report\\/v3?s=b3H4j2%2BmY8qRXW7gGLc0HfqFZcb7KoHIeY%2BUyL6WRg0VR%2FR6lo5JpLOGk2iUtKF6%2BFKD%2FQ5dcqS7PIOo2io%2F2114qSE9AmuGpUqoDMPBaT7h0DleHflpdE21BtAB8D%2Be6zWqZOqqkhQV\"}],\"group\":\"cf-nel\",\"max_age\":604800}",
    "Server": "cloudflare",
    "Set-Cookie": "PHPSESSID=2ah41inof7tdce52fsfvt1t0vb; path=/",
    "Transfer-Encoding": "chunked",
    "Vary": "Accept-Encoding",
    "cf-edge-cache": "cache,platform=wordpress"
  },
  "scan_id": 35874285,
  "score": 0,
  "start_time": "Sat, 01 Apr 2023 01:01:03 GMT",
  "state": "FINISHED",
  "status_code": 200,
  "tests_failed": 7,
  "tests_passed": 5,
  "tests_quantity": 12
}