{
  "algorithm_version": 2,
  "end_time": "Mon, 24 Jul 2023 00:18:45 GMT",
  "grade": "F",
  "hidden": false,
  "likelihood_indicator": "MEDIUM",
  "response_headers": {
    "Cache-Control": "no-store, no-cache, must-revalidate",
    "Connection": "Keep-Alive",
    "Content-Encoding": "gzip",
    "Content-Length": "16454",
    "Content-Type": "text/html; charset=UTF-8",
    "Date": "Mon, 24 Jul 2023 00:18:22 GMT",
    "Expires": "Thu, 19 Nov 1981 08:52:00 GMT",
    "Keep-Alive": "timeout=5, max=100",
    "Link": "<https://www.toledo.es/wp-json/>; rel=\"https://api.w.org/\"",
    "Pragma": "no-cache",
    "Server": "Apache/2.4.6 (CentOS) OpenSSL/1.0.2k-fips PHP/7.0.32",
    "Set-Cookie": "mc_session_ids[default]=f6f831fb6fdba9183f9e6f2852408e1a7bbcc6d6; expires=Mon, 24-Jul-2023 00:23:23 GMT; Max-Age=300; path=/; domain=.toledo.es; secure; HttpOnly, mc_session_ids[multi][0]=3d44e46c1193f4831e583451796e0dc5f3a02ec3; expires=Mon, 24-Jul-2023 00:23:23 GMT; Max-Age=300; path=/; domain=.toledo.es, mc_session_ids[multi][1]=52a52e8bcf30dc4a8989ce34a1a69d9e5a80888f; expires=Mon, 24-Jul-2023 00:23:23 GMT; Max-Age=300; path=/; domain=.toledo.es, mc_session_ids[multi][2]=2e01a241e4988a99ffc83e59c09958c6908a56af; expires=Mon, 24-Jul-2023 00:23:23 GMT; Max-Age=300; path=/; domain=.toledo.es, mc_session_ids[multi][3]=b7915f58ebc9456b9355bd6f3c34fb049cb8c804; expires=Mon, 24-Jul-2023 00:23:23 GMT; Max-Age=300; path=/; domain=.toledo.es, mc_session_ids[multi][4]=fc67fb20006c2a387312211b0e8c957130ef0c71; expires=Mon, 24-Jul-2023 00:23:23 GMT; Max-Age=300; path=/; domain=.toledo.es, PHPSESSID=d4c73254dcbe853e85af19dfa27e2199; path=/; HttpOnly, cf7msm_check=1; path=/; domain=.toledo.es",
    "Vary": "Accept-Encoding",
    "X-Powered-By": "PHP/7.0.32"
  },
  "scan_id": 40031646,
  "score": 0,
  "start_time": "Mon, 24 Jul 2023 00:12:37 GMT",
  "state": "FINISHED",
  "status_code": 200,
  "tests_failed": 7,
  "tests_passed": 5,
  "tests_quantity": 12
}