{
  "algorithm_version": 2,
  "end_time": "Mon, 09 Oct 2023 00:09:10 GMT",
  "grade": "F",
  "hidden": false,
  "likelihood_indicator": "MEDIUM",
  "response_headers": {
    "Cache-Control": "no-store, no-cache, must-revalidate, post-check=0, pre-check=0, no-cache",
    "Connection": "Keep-Alive",
    "Content-Encoding": "gzip",
    "Content-Length": "11492",
    "Content-Type": "text/html; charset=utf-8",
    "Date": "Mon, 09 Oct 2023 00:09:05 GMT",
    "ETag": "\"02bf25b9572d5d5226963439fd835303-gzip\"",
    "Expires": "Wed, 17 Aug 2005 00:00:00 GMT",
    "Keep-Alive": "timeout=5, max=100",
    "Last-Modified": "Mon, 09 Oct 2023 00:04:51 GMT",
    "Pragma": "no-cache",
    "Server": "Apache/2.4.41 (Ubuntu)",
    "Set-Cookie": "c33a21d3e4e875375a974c0625a440d1=t56n34dvv8hkpn3dj8dsek116s; path=/; HttpOnly",
    "Vary": "Accept-Encoding"
  },
  "scan_id": 43032262,
  "score": 0,
  "start_time": "Mon, 09 Oct 2023 00:08:02 GMT",
  "state": "FINISHED",
  "status_code": 200,
  "tests_failed": 7,
  "tests_passed": 5,
  "tests_quantity": 12
}