{
  "algorithm_version": 2,
  "end_time": "Thu, 13 Oct 2022 01:10:05 GMT",
  "grade": "F",
  "hidden": false,
  "likelihood_indicator": "MEDIUM",
  "response_headers": {
    "Accept-ranges": "bytes",
    "Cache-control": "public,max-age=300",
    "Content-length": "46915",
    "Content-type": "text/html",
    "Date": "Thu, 13 Oct 2022 01:09:47 GMT",
    "Etag": "\"b743-6340178c\"",
    "Last-modified": "Fri, 07 Oct 2022 12:11:56 GMT",
    "Server": "Servidor-Web"
  },
  "scan_id": 30088472,
  "score": 15,
  "start_time": "Thu, 13 Oct 2022 01:09:42 GMT",
  "state": "FINISHED",
  "status_code": 200,
  "tests_failed": 6,
  "tests_passed": 6,
  "tests_quantity": 12
}