{
  "algorithm_version": 2,
  "end_time": "Sun, 03 Dec 2023 00:59:10 GMT",
  "grade": "F",
  "hidden": false,
  "likelihood_indicator": "MEDIUM",
  "response_headers": {
    "Cache-Control": "max-age=0, no-cache, no-store",
    "Connection": "keep-alive",
    "Content-Encoding": "gzip",
    "Content-Length": "12868",
    "Content-Type": "text/html;charset=UTF-8",
    "Date": "Sun, 03 Dec 2023 00:58:58 GMT",
    "Expires": "Sun, 03 Dec 2023 00:58:58 GMT",
    "OT-force-Account-Verify": "true",
    "Pragma": "no-cache",
    "Server-Timing": "cdn-cache; desc=MISS, edge; dur=233, origin; dur=136, ak_p; desc=\"1701565138025_399222604_3708417615_37072_6155_9_0_-\";dur=1",
    "Set-Cookie": "JSESSIONID=E1AF15CB9BBED40F72C65AA8F2D8C3DB.app01; Path=/; Secure; HttpOnly, ROUTEID=.app01; path=/",
    "Strict-Transport-Security": "max-age=86400",
    "Vary": "Accept-Encoding",
    "X-Akamai-Transformed": "9 11210 0 pmb=mRUM,1",
    "X-Frame-Options": "SAMEORIGIN",
    "X-UA-Compatible": "IE=8"
  },
  "scan_id": 45130714,
  "score": 0,
  "start_time": "Sun, 03 Dec 2023 00:58:50 GMT",
  "state": "FINISHED",
  "status_code": 200,
  "tests_failed": 6,
  "tests_passed": 6,
  "tests_quantity": 12
}