{
  "algorithm_version": 3,
  "end_time": "Sat, 27 Apr 2024 00:54:51 GMT",
  "grade": "B",
  "hidden": false,
  "likelihood_indicator": "MEDIUM",
  "response_headers": {
    "Accept-Ranges": "bytes",
    "Connection": "Upgrade, Keep-Alive",
    "Content-Encoding": "gzip",
    "Content-Type": "text/html",
    "Date": "Sat, 27 Apr 2024 00:54:48 GMT",
    "Keep-Alive": "timeout=15, max=100",
    "Last-Modified": "Mon, 18 Apr 2022 07:48:09 GMT",
    "Referrer-Policy": "no-referrer-when-downgrade",
    "Set-Cookie": "visid_incap_171420=otXrJCPXQs+jcVGzyRHBDNZMLGYAAAAAQUIPAAAAAAA0h+TUP64YN0ixOQi+tvli; expires=Sat, 26 Apr 2025 06:26:21 GMT; HttpOnly; path=/; Domain=.grancanaria.com; Secure; SameSite=None, nlbi_171420=JQEWIEankhQ0LI823tof+wAAAAAmwBN2euvE288I7S/o382z; path=/; Domain=.grancanaria.com; Secure; SameSite=None, incap_ses_726_171420=X89CIdMHfVHgZL2cMEUTCtdMLGYAAAAAwzXpAE1Z+hB7JIAiSfccuw==; path=/; Domain=.grancanaria.com; Secure; SameSite=None",
    "Strict-Transport-Security": "max-age=31536000",
    "Transfer-Encoding": "chunked",
    "Upgrade": "h2",
    "Vary": "Accept-Encoding",
    "X-CDN": "Imperva",
    "X-Content-Type-Options": "nosniff",
    "X-Frame-Options": "SAMEORIGIN",
    "X-Iinfo": "7-3786859-3786862 NNNY CT(188 189 0) RT(1714179287478 151) q(0 0 0 0) r(2 2) U12",
    "X-XSS-Protection": "1; mode=block"
  },
  "scan_id": 50416737,
  "score": 70,
  "start_time": "Sat, 27 Apr 2024 00:54:46 GMT",
  "state": "FINISHED",
  "status_code": 200,
  "tests_failed": 2,
  "tests_passed": 9,
  "tests_quantity": 11
}