{
  "algorithm_version": 2,
  "end_time": "Fri, 22 Sep 2023 00:52:56 GMT",
  "grade": "F",
  "hidden": false,
  "likelihood_indicator": "MEDIUM",
  "response_headers": {
    "Cache-Control": "no-store, no-cache, must-revalidate",
    "Connection": "Keep-Alive",
    "Content-Encoding": "gzip",
    "Content-Length": "20211",
    "Content-Type": "text/html; charset=UTF-8",
    "Date": "Fri, 22 Sep 2023 00:52:40 GMT",
    "Expires": "Thu, 19 Nov 1981 08:52:00 GMT",
    "Keep-Alive": "timeout=5, max=100",
    "Link": "<https://www.toledo.es/wp-json/>; rel=\"https://api.w.org/\"",
    "Pragma": "no-cache",
    "Server": "Apache/2.4.6 (CentOS) OpenSSL/1.0.2k-fips PHP/7.0.32",
    "Set-Cookie": "mc_session_ids[default]=6e14086f8f590d68948f9b6ca9e438b925da7993; expires=Fri, 22-Sep-2023 00:57:40 GMT; Max-Age=300; path=/; domain=.toledo.es; secure; HttpOnly, mc_session_ids[multi][0]=b6190fffa84e8543a9df88654e0ac974d8d8cdcf; expires=Fri, 22-Sep-2023 00:57:40 GMT; Max-Age=300; path=/; domain=.toledo.es, mc_session_ids[multi][1]=d8446e4c7fef84784ed296c9b6469e9bd6a373a4; expires=Fri, 22-Sep-2023 00:57:40 GMT; Max-Age=300; path=/; domain=.toledo.es, mc_session_ids[multi][2]=e7933d223bd54c61e271cc2cae7098766fc28a57; expires=Fri, 22-Sep-2023 00:57:40 GMT; Max-Age=300; path=/; domain=.toledo.es, mc_session_ids[multi][3]=f51aed33d692318fddf49f7d3c00092b4fc63944; expires=Fri, 22-Sep-2023 00:57:40 GMT; Max-Age=300; path=/; domain=.toledo.es, mc_session_ids[multi][4]=4b7a5e78bf1f8fa9a98069a7b9e816a442d7a71c; expires=Fri, 22-Sep-2023 00:57:40 GMT; Max-Age=300; path=/; domain=.toledo.es, PHPSESSID=943862dfadc8b05e87debd2bbbecb8dd; path=/; HttpOnly, cf7msm_check=1; path=/; domain=.toledo.es",
    "Vary": "Accept-Encoding",
    "X-Powered-By": "PHP/7.0.32"
  },
  "scan_id": 42434817,
  "score": 0,
  "start_time": "Fri, 22 Sep 2023 00:52:19 GMT",
  "state": "FINISHED",
  "status_code": 200,
  "tests_failed": 7,
  "tests_passed": 5,
  "tests_quantity": 12
}