{
  "algorithm_version": 2,
  "end_time": "Fri, 01 Sep 2023 00:54:53 GMT",
  "grade": "B",
  "hidden": false,
  "likelihood_indicator": "MEDIUM",
  "response_headers": {
    "Accept-Ranges": "bytes",
    "Connection": "Keep-Alive",
    "Content-Encoding": "gzip",
    "Content-Type": "text/html",
    "Date": "Fri, 01 Sep 2023 00:54:52 GMT",
    "Keep-Alive": "timeout=15, max=99",
    "Last-Modified": "Mon, 18 Apr 2022 07:48:09 GMT",
    "Referrer-Policy": "no-referrer-when-downgrade",
    "Set-Cookie": "nlbi_171420=suMgOTu9Si2hE0SY3tof+wAAAADUk7HAIXpEX/QWsKbWWgoG; path=/; Domain=.grancanaria.com; Secure; SameSite=None, visid_incap_171420=BB5po2FQRfK4DJ0qywARWFo28WQAAAAAQUIPAAAAAADsvSGEMlWSzot4Qz27Xbb7; expires=Fri, 30 Aug 2024 08:29:01 GMT; HttpOnly; path=/; Domain=.grancanaria.com; Secure; SameSite=None, incap_ses_499_171420=vqWbWeIwPTzYWIYdNs/sBls28WQAAAAAvPwqsYRus4pXVOhZCnzi+g==; path=/; Domain=.grancanaria.com; Secure; SameSite=None",
    "Strict-Transport-Security": "max-age=31536000",
    "Transfer-Encoding": "chunked",
    "Vary": "Accept-Encoding",
    "X-CDN": "Imperva",
    "X-Content-Type-Options": "nosniff",
    "X-Frame-Options": "SAMEORIGIN",
    "X-Iinfo": "4-23020311-22944878 pNNy RT(1693529691175 43) q(0 0 0 5) r(2 2) U12",
    "X-XSS-Protection": "1; mode=block"
  },
  "scan_id": 41525122,
  "score": 70,
  "start_time": "Fri, 01 Sep 2023 00:54:49 GMT",
  "state": "FINISHED",
  "status_code": 200,
  "tests_failed": 2,
  "tests_passed": 10,
  "tests_quantity": 12
}