{
  "algorithm_version": 3,
  "end_time": "Sun, 14 Jul 2024 00:52:07 GMT",
  "grade": "F",
  "hidden": false,
  "likelihood_indicator": "MEDIUM",
  "response_headers": {
    "Accept-Ranges": "bytes",
    "Access-Control-Allow-Origin": "*",
    "Age": "2648013",
    "Cache-Control": "s-maxage=120, public",
    "Connection": "keep-alive",
    "Content-Length": "455",
    "Content-Type": "text/html; charset=UTF-8",
    "Date": "Thu, 13 Jun 2024 09:18:31 GMT",
    "ETag": "W/\"455-1490177218000\"",
    "Last-Modified": "Wed, 22 Mar 2017 10:06:58 GMT",
    "Server": "Apache-Coyote/1.1",
    "Via": "1.1 d18c8670421cff5c9fa297b260cb2814.cloudfront.net (CloudFront)",
    "X-Amz-Cf-Id": "NHW69HhQjZrEPqEmyod5rrMB1ZYpoFccY0zTsiocaFVIKsxtf4GRYA==",
    "X-Amz-Cf-Pop": "DEN53-P2",
    "X-Cache": "Hit from cloudfront"
  },
  "scan_id": 53366406,
  "score": 0,
  "start_time": "Sun, 14 Jul 2024 00:52:04 GMT",
  "state": "FINISHED",
  "status_code": 200,
  "tests_failed": 6,
  "tests_passed": 5,
  "tests_quantity": 11
}